core_evals/garak/__init__.py
core_evals/garak/framework.yml
core_evals/garak/framework_entrypoint.py
core_evals/garak/output.py
nvidia_eval_factory_garak-25.11.dist-info/licenses/LICENSE
nvidia_eval_factory_garak-25.11.dist-info/METADATA
nvidia_eval_factory_garak-25.11.dist-info/WHEEL
nvidia_eval_factory_garak-25.11.dist-info/top_level.txt
nvidia_eval_factory_garak-25.11.dist-info/RECORD
