Metadata-Version: 2.4
Name: nvidia-eval-factory-garak
Version: 25.11
Summary: garak (LLM vulnerability scanner) - packaged by NVIDIA Eval Factory
Author: nv052193, Mads Kongsbak, Tianhao Li, Phyllis Poh, Razvan Dinu, Zander Mackie, Greg Stephens, Ahsan Ayub, Jonathan Liberman, Gustav Fredrikson, Oh Tien Cheng, Brain John, Naman Mishra, Soumili Nandi, Arjun Krishna, Mihailo Milenkovic, Kai Greshake, Martin Borup-Larsen, Emmanuel Ferdman, Eric Therond, Zoe Nolan, Harsh Raj, Shine-afk, Rafael Sandroni, Eric Hacker, Blessed Uyo, Ikko Eltociear Ashimine, iamnotcj, Dwight Temple, Shane Rosse, Masaya Ogushi, Viktor T. Zetterberg, Erwan Roussel, 
Author-email: Leon Derczynski <lderczynski@nvidia.com>, Subho Majumdar <subho@vijil.ai>, Erick Galinkin <egalinkin@nvidia.com>, Jeffrey Martin <jemartin@nvidia.com>
License: 
Project-URL: Homepage, https://github.com/NVIDIA/garak
Project-URL: Bug Tracker, https://github.com/NVIDIA/garak/issues
Classifier: Development Status :: 5 - Production/Stable
Classifier: Programming Language :: Python :: 3
Classifier: License :: OSI Approved :: Apache Software License
Classifier: Operating System :: OS Independent
Requires-Python: >=3.10
License-File: LICENSE
Requires-Dist: garak~=0.13
Requires-Dist: nemo-evaluator
Dynamic: license-file
